[{"assignees":[],"labels":[],"number":255,"title":"chore(deps-dev): bump vite from 6.4.1 to 7.2.4 in /frontend","updatedAt":"2025-11-24T20:56:59Z","url":"https://github.com/suporterfid/pdf-knowledge-kit/pull/255"},{"assignees":[],"labels":[],"number":254,"title":"chore(deps-dev): bump typescript-eslint from 8.47.0 to 8.48.0 in /frontend","updatedAt":"2025-11-24T20:56:50Z","url":"https://github.com/suporterfid/pdf-knowledge-kit/pull/254"},{"assignees":[],"labels":[],"number":253,"title":"chore(deps-dev): bump @typescript-eslint/eslint-plugin from 8.47.0 to 8.48.0 in /frontend","updatedAt":"2025-11-24T20:56:33Z","url":"https://github.com/suporterfid/pdf-knowledge-kit/pull/253"},{"assignees":[],"labels":[],"number":252,"title":"chore(deps-dev): bump msw from 2.10.5 to 2.12.3 in /frontend","updatedAt":"2025-11-24T20:56:21Z","url":"https://github.com/suporterfid/pdf-knowledge-kit/pull/252"},{"assignees":[],"labels":[],"number":251,"title":"chore(deps-dev): bump vitest from 4.0.10 to 4.0.13 in /frontend","updatedAt":"2025-11-24T20:56:14Z","url":"https://github.com/suporterfid/pdf-knowledge-kit/pull/251"},{"assignees":[],"labels":[],"number":250,"title":"chore(deps-dev): bump @typescript-eslint/parser from 8.47.0 to 8.48.0 in /frontend","updatedAt":"2025-11-24T20:55:54Z","url":"https://github.com/suporterfid/pdf-knowledge-kit/pull/250"},{"assignees":[],"labels":[],"number":249,"title":"chore(deps): bump actions/checkout from 4 to 6","updatedAt":"2025-11-24T20:51:43Z","url":"https://github.com/suporterfid/pdf-knowledge-kit/pull/249"}]
